odoo/addons/budget_activity_purchase_request/README.rst
odoo/addons/budget_activity_purchase_request/__init__.py
odoo/addons/budget_activity_purchase_request/__manifest__.py
odoo/addons/budget_activity_purchase_request/models/__init__.py
odoo/addons/budget_activity_purchase_request/models/purchase_request.py
odoo/addons/budget_activity_purchase_request/readme/CONTRIBUTORS.md
odoo/addons/budget_activity_purchase_request/readme/DESCRIPTION.md
odoo/addons/budget_activity_purchase_request/readme/USAGE.md
odoo/addons/budget_activity_purchase_request/static/description/icon.png
odoo/addons/budget_activity_purchase_request/static/description/index.html
odoo/addons/budget_activity_purchase_request/tests/__init__.py
odoo/addons/budget_activity_purchase_request/tests/test_budget_activity_purchase_request.py
odoo/addons/budget_activity_purchase_request/views/purchase_request_budget_move.xml
odoo/addons/budget_activity_purchase_request/views/purchase_request_line_view.xml
odoo/addons/budget_activity_purchase_request/views/purchase_request_view.xml
odoo/addons/budget_activity_purchase_request/views/purchase_views.xml
odoo/addons/budget_activity_purchase_request/wizard/__init__.py
odoo/addons/budget_activity_purchase_request/wizard/purchase_line_make_purchase_order.py
odoo_addon_budget_activity_purchase_request-18.0.1.0.0.1.dist-info/METADATA
odoo_addon_budget_activity_purchase_request-18.0.1.0.0.1.dist-info/WHEEL
odoo_addon_budget_activity_purchase_request-18.0.1.0.0.1.dist-info/top_level.txt
odoo_addon_budget_activity_purchase_request-18.0.1.0.0.1.dist-info/RECORD
